file2text/__init__.py
file2text/file2text.py
file2text-0.1.0.dist-info/LICENSE
file2text-0.1.0.dist-info/METADATA
file2text-0.1.0.dist-info/WHEEL
file2text-0.1.0.dist-info/RECORD
