Metadata-Version: 2.1
Name: file2text
Version: 0.1.0
Summary: Python package to read pdf / word file and extract text from it.
License: MIT
Author: Beth Ou Yang
Requires-Python: >=3.11,<4.0
Classifier: License :: OSI Approved :: MIT License
Classifier: Programming Language :: Python :: 3
Classifier: Programming Language :: Python :: 3.11
Classifier: Programming Language :: Python :: 3.12
Requires-Dist: python-docx (>=1.1.0,<2.0.0)
